MANIFEST.in
README.rst
__init__.py
setup.py
bin/shortpath
shortpath/__init__.py
shortpath/shortpath.py
shortpath.egg-info/PKG-INFO
shortpath.egg-info/SOURCES.txt
shortpath.egg-info/dependency_links.txt
shortpath.egg-info/requires.txt
shortpath.egg-info/top_level.txt