Metadata-Version: 1.0
Name: shortpath
Version: 1.0.2
Summary: Shortpath provides a small name for your long project paths.
Home-page: https://github.com/aavrug/shortpath.git
Author: Gaurav Kumar
Author-email: aavrug@gmail.com
License: MIT
Keywords: shortpath
Platform: UNKNOWN
